mxnet_to_coreml-0.1.3.data/purelib/converter/__init__.py
mxnet_to_coreml-0.1.3.data/purelib/converter/_add_pooling.py
mxnet_to_coreml-0.1.3.data/purelib/converter/_layers.py
mxnet_to_coreml-0.1.3.data/purelib/converter/_mxnet_converter.py
mxnet_to_coreml-0.1.3.data/purelib/converter/utils.py
mxnet_to_coreml-0.1.3.data/scripts/mxnet_coreml_converter.py
mxnet_to_coreml-0.1.3.dist-info/METADATA
mxnet_to_coreml-0.1.3.dist-info/RECORD
mxnet_to_coreml-0.1.3.dist-info/WHEEL
mxnet_to_coreml-0.1.3.dist-info/top_level.txt
