Metadata-Version: 2.1
Name: mxnet-to-coreml
Version: 0.1.3
Summary: Tool to convert MXNet models into Apple CoreML model format.
Home-page: https://github.com/apache/incubator-mxnet/tree/master/tools/coreml
Author: pracheer
Author-email: pracheer_gupta@hotmail.com
License: Apache 2.0
Keywords: Apache MXNet Apple CoreML Converter Deep Learning
Platform: UNKNOWN
Classifier: Development Status :: 4 - Beta
Classifier: Intended Audience :: Developers
Classifier: License :: OSI Approved :: Apache Software License
Classifier: Operating System :: MacOS :: MacOS X
Classifier: Programming Language :: Python :: 2.7
Classifier: Topic :: Software Development :: Libraries :: Python Modules
Requires-Python: ~=2.7
Requires-Dist: mxnet
Requires-Dist: coremltools
Requires-Dist: pyyaml
